{
  "module_note": "tabsPrivate implementation is in external chunk 17885 (66x required) - NOT in this bundle",
  "access_patterns": {
    "A.Z.tabsPrivate": "Main tabsPrivate access (from chunk 17885)",
    "N.Z.tabsPrivate": "Secondary tabsPrivate (requires N assignment)",
    "h.Z.tabsPrivate": "Event listeners (onDragEnd, onKeyboardChanged, etc.)",
    "s.Z.tabsPrivate": "Tab operations"
  },
  "startDrag_signature": {
    "windowId": "Target window ID",
    "mimeType": "Drag MIME type (f.Up = vivaldi/x-tab)",
    "customData": "JSON: {ids: number[], active: number, ...}",
    "url": "Tab URL",
    "title": "Tab title",
    "posX": "Left position from rect calculation (o.left + offsetX)",
    "posY": "Top position from rect calculation (o.top + offsetY)",
    "width": "Width from rect calculation (o.width + offsetX)",
    "height": "Height from rect calculation (o.height + offsetY)",
    "cursorX": "Cursor X (default 10)",
    "cursorY": "Cursor Y (default 10)"
  },
  "methods_called": [
    "A.Z.tabsPrivate.onDragEnd.addListener",
    "A.Z.tabsPrivate.startDrag",
    "A.Z.tabsPrivate.update",
    "h.Z.tabsPrivate.onKeyboardChanged",
    "h.Z.tabsPrivate.onMouseChanged",
    "h.Z.tabsPrivate.onPageZoom"
  ]
}